amfTools/__init__.py
amftools-0.1.10.dist-info/licenses/licence
amftools-0.1.10.dist-info/METADATA
amftools-0.1.10.dist-info/WHEEL
amftools-0.1.10.dist-info/top_level.txt
amftools-0.1.10.dist-info/RECORD
