Metadata-Version: 2.4
Name: AMFTools
Version: 0.1.10
Summary: AMF Tools is a python package to control Advanced Microfluics SA devices
Home-page: https://amf.ch
Author: Advanced_Microfluidics_SA
Author-email: support@amf.ch
License: proprietary license (Advanced Microfluidics SA)
Classifier: Programming Language :: Python :: 3
Classifier: Development Status :: 5 - Production/Stable
Classifier: Programming Language :: Python :: 3.11
Classifier: Topic :: Security
Requires-Python: >=3.8
License-File: licence
Requires-Dist: pyserial
Requires-Dist: ftd2xx
Dynamic: author
Dynamic: author-email
Dynamic: classifier
Dynamic: description
Dynamic: description-content-type
Dynamic: home-page
Dynamic: license
Dynamic: license-file
Dynamic: requires-dist
Dynamic: requires-python
Dynamic: summary
